[{
        "id": "1",
        "name": "ศิลปศาสตร์",
        "parent_id": "0"
    },
    {
        "id": "2",
        "name": "ครุศาสตร์อุตสาหกรรม",
        "parent_id": "0"
    },
    {
        "id": "3",
        "name": "เทคโนโลยีการเกษตร",
        "parent_id": "0"
    },
    {
        "id": "4",
        "name": "วิศวกรรมศาสตร์",
        "parent_id": "0"
    },
    {
        "id": "5",
        "name": "บริหารธุรกิจ",
        "parent_id": "0"
    },
    {
        "id": "6",
        "name": "เทคโนโลยีคหกรรมศาสตร์",
        "parent_id": "0"
    },
    {
        "id": "7",
        "name": "ศิลปกรรมศาสตร์",
        "parent_id": "0"
    },
    {
        "id": "8",
        "name": "เทคโนโลยีสื่อสารมวลชน",
        "parent_id": "0"
    },
    {
        "id": "9",
        "name": "วิทยาศาสตร์และเทคโนโลยี",
        "parent_id": "0"
    },
    {
        "id": "10",
        "name": "สถาปัตยกรรมศาสตร์",
        "parent_id": "0"
    },
    {
        "id": "11",
        "name": "วิทยาลัยการแพทย์แผนไทย",
        "parent_id": "0"
    },
    {
        "id": "12",
        "name": "พยาบาลศาสตร์",
        "parent_id": "0"
    },
    {
        "name": "การจัดการการโรงแรม",
        "parent_id": "1"
    },
    {
        "name": "การท่องเที่ยว",
        "parent_id": "1"
    },
    {
        "name": "ภาษาอังกฤษเพื่อการสื่อสาร",
        "parent_id": "1"
    },
    {
        "name": "อุตสาหกรรมการบริการการบิน",
        "parent_id": "1"
    },
    {
        "name": "วิศวกรรมคอมพิวเตอร์",
        "parent_id": "2"
    },
    {
        "name": "วิศวกรรมเครื่องกล",
        "parent_id": "2"
    },
    {
        "name": "วิศวกรรมไฟฟ้า",
        "parent_id": "2"
    },
    {
        "name": "วิศวกรรมโยธา",
        "parent_id": "2"
    },
    {
        "name": "วิศวกรรมอิเล็กทรอนิกส์และโทรคมนาคม-โทรคมนาคม",
        "parent_id": "2"
    },
    {
        "name": "วิศวกรรมอุตสาหการ",
        "parent_id": "2"
    },
    {
        "name": "วิศวกรรมเมคคาทรอนิกส์",
        "parent_id": "2"
    },
    {
        "name": "คอมพิวเตอร์ศึกษา",
        "parent_id": "2"
    },
    {
        "name": "เทคโนโลยีและสื่อสารการศึกษา",
        "parent_id": "2"
    },
    {
        "name": "เทคโนโลยีสารสนเทศการศึกษา",
        "parent_id": "2"
    },
    {
        "name": "เทคโนโลยีการผลิต",
        "parent_id": "2"
    },
    {
        "name": "อุตสาหกรรมการผลิต",
        "parent_id": "2"
    },
    {
        "name": "การผลิตพืช",
        "parent_id": "3"
    },
    {
        "name": "เทคโนโลยีภูมิทัศน์",
        "parent_id": "3"
    },
    {
        "name": "ประมง",
        "parent_id": "3"
    },
    {
        "name": "วิทยาศาสตร์และเทคโนโลยีการอาหาร",
        "parent_id": "3"
    },
    {
        "name": "วิทยาศาสตร์สุขภาพสัตว์",
        "parent_id": "3"
    },
    {
        "name": "สัตวศาสตร์",
        "parent_id": "3"
    },
    {
        "name": "วิศวกรรมคอมพิวเตอร์",
        "parent_id": "4"
    },
    {
        "name": "วิศวกรรมเคมี",
        "parent_id": "4"
    },
    {
        "name": "วิศวกรรมเคมีสิ่งทอและเส้นใย - เคมีและสีสิ่งทอ",
        "parent_id": "4"
    },
    {
        "name": "วิศวกรรมเคมีสิ่งทอและเส้นใย - พอลิเมอร์และเส้นใย",
        "parent_id": "4"
    },
    {
        "name": "วิศวกรรมเครื่องกล",
        "parent_id": "4"
    },
    {
        "name": "วิศวกรรมเครื่องกล-วิศวกรรมระบบราง",
        "parent_id": "4"
    },
    {
        "name": "อุตสาหกรรมการผลิต",
        "parent_id": "4"
    },
    {
        "name": "วิศวกรรมเครื่องจักรกลเกษตร",
        "parent_id": "4"
    },
    {
        "name": "วิศวกรรมชลประทานและการจัดการน้ำ",
        "parent_id": "4"
    },
    {
        "name": "วิศวกรรมไฟฟ้า",
        "parent_id": "4"
    },
    {
        "name": "วิศวกรรมโยธา",
        "parent_id": "4"
    },
    {
        "name": "วิศวกรรมวัสดุ-วิศวกรรมพลาสติก",
        "parent_id": "4"
    },
    {
        "name": "วิศวกรรมวัสดุ-วิศวกรรมพอลิเมอร์",
        "parent_id": "4"
    },
    {
        "name": "วิศวกรรมสิ่งทอ - วิศวกรรมเครื่องนุ่งห่ม",
        "parent_id": "4"
    },
    {
        "name": "วิศวกรรมสิ่งแวดล้อม",
        "parent_id": "4"
    },
    {
        "name": "วิศวกรรมอาหาร",
        "parent_id": "4"
    },
    {
        "name": "วิศวกรรมอิเล็กทรอนิกส์และโทรคมนาคม-วิศวกรรมโทรคมนาคม",
        "parent_id": "4"
    },
    {
        "name": "วิศวกรรมอิเล็กทรอนิกส์และโทรคมนาคม-วิศวกรรมสื่อสารโครงข่าย",
        "parent_id": "4"
    },
    {
        "name": "วิศวกรรมอิเล็กทรอนิกส์และโทรคมนาคม-วิศวกรรมอิเล็กทรอนิกส์",
        "parent_id": "4"
    },
    {
        "name": "วิศวกรรมอุตสาหการ-วิศวกรรมการผลิต",
        "parent_id": "4"
    },
    {
        "name": "วิศวกรรมอุตสาหการ-วิศวกรรมอุตสาหการ",
        "parent_id": "4"
    },
    {
        "name": "การเงิน",
        "parent_id": "5"
    },
    {
        "name": "การจัดการ-การจัดการทรัพยากรมนุษย์",
        "parent_id": "5"
    },
    {
        "name": "การจัดการ-การจัดการทั่วไป",
        "parent_id": "5"
    },
    {
        "name": "การจัดการโลจิสติกส์และซัพพลายเชน",
        "parent_id": "5"
    },
    {
        "name": "การตลาด",
        "parent_id": "5"
    },
    {
        "name": "การบริหารธุรกิจระหว่างประเทศ",
        "parent_id": "5"
    },
    {
        "name": "คอมพิวเตอร์ธุรกิจ",
        "parent_id": "5"
    },
    {
        "name": "เศรษฐศาสตร์-เศรษฐศาสตร์ธุรกิจ",
        "parent_id": "5"
    },
    {
        "name": "เศรษฐศาสตร์-เศรษฐศาสตร์ระหว่างประเทศ",
        "parent_id": "5"
    },
    {
        "name": "การออกแบบแฟชั่นและเครื่องแต่งกาย",
        "parent_id": "6"
    },
    {
        "name": "เทคโนโลยีงานประดิษฐ์สร้างสรรค์",
        "parent_id": "6"
    },
    {
        "name": "อาหารและโภชนาการ",
        "parent_id": "6"
    },
    {
        "name": "อุตสาหกรรมบริการอาหาร",
        "parent_id": "6"
    },
    {
        "name": "การศึกษาปฐมวัย",
        "parent_id": "6"
    },
    {
        "name": "จิตรกรรม",
        "parent_id": "7"
    },
    {
        "name": "ดนตรีสากล",
        "parent_id": "7"
    },
    {
        "name": "นวัตกรรมการออกแบบผลิตภัณฑ์ร่วมสมัย",
        "parent_id": "7"
    },
    {
        "name": "ประติมากรรม",
        "parent_id": "7"
    },
    {
        "name": "ศิลปะไทย",
        "parent_id": "7"
    },
    {
        "name": "ศิลปะภาพพิมพ์",
        "parent_id": "7"
    },
    {
        "name": "ออกแบบนิเทศศิลป์",
        "parent_id": "7"
    },
    {
        "name": "ออกแบบผลิตภัณฑ์",
        "parent_id": "7"
    },
    {
        "name": "ออกแบบภายใน",
        "parent_id": "7"
    },
    {
        "name": "ดนตรีคีตศิลป์ไทยศึกษา",
        "parent_id": "7"
    },
    {
        "name": "ดนตรีคีตศิลป์สากลศึกษา",
        "parent_id": "7"
    },
    {
        "name": "นาฏศิลป์ไทยศึกษา",
        "parent_id": "7"
    },
    {
        "name": "เทคโนโลยีการโฆษณาและประชาสัมพันธ์",
        "parent_id": "8"
    },
    {
        "name": "เทคโนโลยีการถ่ายภาพและภาพยนตร์",
        "parent_id": "8"
    },
    {
        "name": "เทคโนโลยีการโทรทัศน์และวิทยุกระจายเสียง",
        "parent_id": "8"
    },
    {
        "name": "เทคโนโลยีการพิมพ์ดิจิทัลและบรรจุภัณฑ์",
        "parent_id": "8"
    },
    {
        "name": "เทคโนโลยีมัลติมีเดีย",
        "parent_id": "8"
    },
    {
        "name": "คณิตศาสตร์",
        "parent_id": "9"
    },
    {
        "name": "เคมี",
        "parent_id": "9"
    },
    {
        "name": "ชีววิทยาประยุกต์",
        "parent_id": "9"
    },
    {
        "name": "เทคโนโลยีสารสนเทศ",
        "parent_id": "9"
    },
    {
        "name": "ฟิสิกส์ประยุกต์",
        "parent_id": "9"
    },
    {
        "name": "วิทยาการคอมพิวเตอร์",
        "parent_id": "9"
    },
    {
        "name": "สถิติประยุกต์",
        "parent_id": "9"
    },
    {
        "name": "สถาปัตยกรรม",
        "parent_id": "10"
    },
    {
        "name": "สถาปัตยกรรมภายใน",
        "parent_id": "10"
    },
    {
        "name": "การแพทย์แผนไทยประยุกต์บัณฑิต",
        "parent_id": "11"
    },
    {
        "name": "สุขภาพและความงาม",
        "parent_id": "11"
    },
    {
        "name": "พยาบาลศาสตรบัณฑิต",
        "parent_id": "12"
    }
]